Assets/__init__.py
Assets/Audio/__init__.py
Assets/Audio/audio_control.py
Assets/Battle_System/__init__.py
Assets/Battle_System/battle_request.py
Assets/Battle_System/neo_battlesystem.py
Assets/Global_Vars/__init__.py
Assets/Global_Vars/maps_data.py
Assets/Health_Attack/__init__.py
Assets/Health_Attack/attacks.py
Assets/Health_Attack/defenses.py
Assets/Health_Attack/enemies.py
Assets/Health_Attack/items.py
Assets/Health_Attack/merchants.py
Assets/Health_Attack/money_manager.py
Assets/Health_Attack/stats.py
Assets/Health_Attack/status_screen.py
Assets/Health_Attack/swords.py
Assets/Visuals/__init__.py
Assets/Visuals/neo_animation_system.py
nyckelmastaren_casahl-1.1.2.dist-info/LICENSE
nyckelmastaren_casahl-1.1.2.dist-info/METADATA
nyckelmastaren_casahl-1.1.2.dist-info/WHEEL
nyckelmastaren_casahl-1.1.2.dist-info/top_level.txt
nyckelmastaren_casahl-1.1.2.dist-info/RECORD
