Metadata-Version: 2.1
Name: nyckelmastaren-casahl
Version: 1.1.2
Summary: A fun retro adventure game.
Home-page: https://github.com/CaspianA1/Nyckelmastaren
Author: Caspian Ahlberg
Author-email: caspianahlberg@gmail.com
License: UNKNOWN
Platform: UNKNOWN
Classifier: Programming Language :: Python :: 3
Classifier: License :: OSI Approved :: GNU General Public License (GPL)
Classifier: Operating System :: OS Independent
Requires-Python: >=3.7
